dyad_git/__init__.py
dyad_git/agent.py
dyad_git/dyad-extension.toml
dyad_git/py.typed
dyad_git-0.1.7.dist-info/METADATA
dyad_git-0.1.7.dist-info/WHEEL
dyad_git-0.1.7.dist-info/RECORD
